working_tree/__init__.py
working_tree/tree.py
working_tree-0.0.2.dist-info/METADATA
working_tree-0.0.2.dist-info/WHEEL
working_tree-0.0.2.dist-info/top_level.txt
working_tree-0.0.2.dist-info/RECORD
